[
  {
    "timestamp": 1743535397.623608,
    "signal": 2
  },
  {
    "timestamp": 1743535399.6244686,
    "signal": 0
  },
  {
    "timestamp": 1743535401.4318786,
    "signal": 1
  },
  {
    "timestamp": 1743535402.6759782,
    "signal": 0
  },
  {
    "timestamp": 1743535403.4306333,
    "signal": 0
  },
  {
    "timestamp": 1743535403.4654453,
    "signal": 1
  },
  {
    "timestamp": 1743535404.175126,
    "signal": 2
  },
  {
    "timestamp": 1743535404.9765286,
    "signal": 0
  },
  {
    "timestamp": 1743535405.5044777,
    "signal": 0
  },
  {
    "timestamp": 1743535405.620962,
    "signal": 2
  },
  {
    "timestamp": 1743535406.4266036,
    "signal": 0
  },
  {
    "timestamp": 1743535406.4845283,
    "signal": 0
  },
  {
    "timestamp": 1743535407.4174068,
    "signal": 1
  },
  {
    "timestamp": 1743535407.6165438,
    "signal": 0
  },
  {
    "timestamp": 1743535408.082976,
    "signal": 0
  },
  {
    "timestamp": 1743535409.4251838,
    "signal": 0
  },
  {
    "timestamp": 1743535409.7990787,
    "signal": 1
  },
  {
    "timestamp": 1743535410.4255998,
    "signal": 0
  },
  {
    "timestamp": 1743535411.8066146,
    "signal": 0
  },
  {
    "timestamp": 1743535419.371288,
    "signal": 1
  },
  {
    "timestamp": 1743535421.3737931,
    "signal": 0
  },
  {
    "timestamp": 1743535428.8169377,
    "signal": 2
  },
  {
    "timestamp": 1743535430.8301241,
    "signal": 0
  },
  {
    "timestamp": 1743535439.906716,
    "signal": 1
  },
  {
    "timestamp": 1743535441.9147215,
    "signal": 0
  },
  {
    "timestamp": 1743535456.18828,
    "signal": 2
  },
  {
    "timestamp": 1743535458.184514,
    "signal": 0
  },
  {
    "timestamp": 1743535466.9878678,
    "signal": 1
  },
  {
    "timestamp": 1743535468.989577,
    "signal": 0
  },
  {
    "timestamp": 1743535474.3922231,
    "signal": 2
  },
  {
    "timestamp": 1743535476.3783793,
    "signal": 0
  },
  {
    "timestamp": 1743535487.4756968,
    "signal": 1
  },
  {
    "timestamp": 1743535489.4632888,
    "signal": 0
  },
  {
    "timestamp": 1743535495.4755762,
    "signal": 2
  },
  {
    "timestamp": 1743535497.4701202,
    "signal": 0
  },
  {
    "timestamp": 1743535504.653262,
    "signal": 1
  },
  {
    "timestamp": 1743535506.5901847,
    "signal": 0
  },
  {
    "timestamp": 1743535507.72653,
    "signal": 2
  },
  {
    "timestamp": 1743535509.557354,
    "signal": 0
  },
  {
    "timestamp": 1743535509.9798205,
    "signal": 0
  },
  {
    "timestamp": 1743535512.0014856,
    "signal": 2
  },
  {
    "timestamp": 1743535514.004715,
    "signal": 0
  },
  {
    "timestamp": 1743535519.5860817,
    "signal": 1
  },
  {
    "timestamp": 1743535521.5825543,
    "signal": 0
  },
  {
    "timestamp": 1743535528.5054107,
    "signal": 2
  },
  {
    "timestamp": 1743535530.5050123,
    "signal": 0
  },
  {
    "timestamp": 1743535538.0270135,
    "signal": 1
  },
  {
    "timestamp": 1743535540.0298073,
    "signal": 0
  },
  {
    "timestamp": 1743535548.5035655,
    "signal": 2
  },
  {
    "timestamp": 1743535550.5061767,
    "signal": 0
  },
  {
    "timestamp": 1743535556.6189833,
    "signal": 1
  },
  {
    "timestamp": 1743535558.6255593,
    "signal": 0
  },
  {
    "timestamp": 1743535563.7421165,
    "signal": 2
  },
  {
    "timestamp": 1743535565.7387853,
    "signal": 0
  },
  {
    "timestamp": 1743535569.4183342,
    "signal": 0
  }
]